pSyCH/__init__.py
pSyCH/scheduler.py
pSyCH/server.py
pSyCH/task.py
pSyCH/tests.py
pSyCH/utils.py
pSyCH-1.0.0.dist-info/LICENSE
pSyCH-1.0.0.dist-info/METADATA
pSyCH-1.0.0.dist-info/WHEEL
pSyCH-1.0.0.dist-info/top_level.txt
pSyCH-1.0.0.dist-info/RECORD
